ghga_validator/__init__.py
ghga_validator/__main__.py
ghga_validator/cli.py
ghga_validator/schema_utils.py
ghga_validator/utils.py
ghga_validator/core/__init__.py
ghga_validator/core/models.py
ghga_validator/core/validator.py
ghga_validator/my_linkml/__init__.py
ghga_validator/my_linkml/object_iterator.py
ghga_validator/plugins/base_plugin.py
ghga_validator/plugins/jsonschema_validation.py
ghga_validator/plugins/ref_validation.py
ghga_validator/plugins/unique_identifier_validation.py
ghga_validator/plugins/utils.py
ghga_validator-1.2.0.dist-info/LICENSE
ghga_validator-1.2.0.dist-info/METADATA
ghga_validator-1.2.0.dist-info/WHEEL
ghga_validator-1.2.0.dist-info/entry_points.txt
ghga_validator-1.2.0.dist-info/top_level.txt
ghga_validator-1.2.0.dist-info/RECORD
