Metadata-Version: 2.1
Name: ghga_validator
Version: 1.2.0
Summary: GHGA Validator - A Python library and command line utility to validate metadata
Author-email: "German Human Genome Phenome Archive (GHGA)" <contact@ghga.de>
License: Apache 2.0
Project-URL: Repository, https://github.com/ghga-de/ghga-validator
Classifier: Development Status :: 1 - Planning
Classifier: Operating System :: POSIX :: Linux
Classifier: Programming Language :: Python :: 3.9
Classifier: Programming Language :: Python :: 3.10
Classifier: Programming Language :: Python :: 3.11
Classifier: License :: OSI Approved :: Apache Software License
Classifier: Topic :: Internet :: WWW/HTTP :: HTTP Servers
Classifier: Topic :: Software Development :: Libraries
Classifier: Intended Audience :: Developers
Requires-Python: >=3.9
License-File: LICENSE
Requires-Dist: typer >=0.9.0
Requires-Dist: pydantic <3,>=2
Requires-Dist: linkml ==1.6.1
Requires-Dist: linkml-runtime ==1.6.0
Requires-Dist: linkml-validator ==0.4.5
Requires-Dist: setuptools ==69.1.1
